amicrt/__init__.py
amicrt/amicrt.py
amicrt/conditionals.py
amicrt/statistics.py
amicrt/utils.py
amicrt-0.1.1.dist-info/LICENSE
amicrt-0.1.1.dist-info/METADATA
amicrt-0.1.1.dist-info/WHEEL
amicrt-0.1.1.dist-info/top_level.txt
amicrt-0.1.1.dist-info/RECORD
